whadup/__init__.py
whadup/core.py
whadup-0.2.0.dist-info/LICENSE
whadup-0.2.0.dist-info/METADATA
whadup-0.2.0.dist-info/WHEEL
whadup-0.2.0.dist-info/top_level.txt
whadup-0.2.0.dist-info/RECORD
