Metadata-Version: 2.1
Name: whadup
Version: 0.2.0
Summary: A python wrapper around githubstatus.com.
Home-page: https://github.com/barnumbirr/whadup
Download-URL: https://github.com/barnumbirr/whadup/archive/refs/heads/master.zip
Author: Martin Simon
Author-email: me@martinsimon.me
License: UNKNOWN
Keywords: Github,Github status,API,wrapper,api
Platform: UNKNOWN
Classifier: Development Status :: 5 - Production/Stable
Classifier: Intended Audience :: Developers
Classifier: Operating System :: OS Independent
Classifier: Programming Language :: Python :: 3
Classifier: Programming Language :: Python :: 3.9
Classifier: Programming Language :: Python :: 3.10
Classifier: Topic :: Utilities
License-File: LICENSE
Requires-Dist: requests
